mcp_ui_server/__init__.py
mcp_ui_server/core.py
mcp_ui_server/exceptions.py
mcp_ui_server/types.py
mcp_ui_server/utils.py
mcp_ui_server-1.0.0.dist-info/METADATA
mcp_ui_server-1.0.0.dist-info/WHEEL
mcp_ui_server-1.0.0.dist-info/RECORD
