Metadata-Version: 2.4
Name: mcp-ui-server
Version: 1.0.0
Summary: mcp-ui Server SDK for Python
Project-URL: Homepage, https://mcpui.dev
Project-URL: Repository, https://github.com/idosal/mcp-ui
Project-URL: Documentation, https://mcpui.dev/guide/introduction
Author: MCP UI Contributors
License: Apache-2.0
Classifier: Development Status :: 4 - Beta
Classifier: Intended Audience :: Developers
Classifier: License :: OSI Approved :: Apache Software License
Classifier: Programming Language :: Python :: 3
Classifier: Programming Language :: Python :: 3.10
Classifier: Programming Language :: Python :: 3.11
Classifier: Programming Language :: Python :: 3.12
Requires-Python: >=3.10
Requires-Dist: mcp>=1.0.0
Requires-Dist: pydantic>=2.0.0
Requires-Dist: typing-extensions>=4.0.0
Provides-Extra: dev
Requires-Dist: pyright>=1.1.0; extra == 'dev'
Requires-Dist: pytest>=7.0.0; extra == 'dev'
Requires-Dist: ruff>=0.1.0; extra == 'dev'
